onlinezip/OnlineZip.py
onlinezip/__init__.py
tests/__init__.py
tests/test_units.py
onlinezip-0.0.2.dist-info/LICENCE
onlinezip-0.0.2.dist-info/METADATA
onlinezip-0.0.2.dist-info/WHEEL
onlinezip-0.0.2.dist-info/top_level.txt
onlinezip-0.0.2.dist-info/RECORD
