Metadata-Version: 2.1
Name: onlinezip
Version: 0.0.2
Summary: Reading zip file through network
Author: Krzysztof Gonia
License: UNKNOWN
Project-URL: Github, https://github.com/kgonia/onlinezip
Platform: UNKNOWN
Classifier: Programming Language :: Python :: 3
Classifier: License :: OSI Approved :: GNU General Public License v3 or later (GPLv3+)
Classifier: Operating System :: OS Independent
Requires-Python: >=3.6
License-File: LICENCE
